autocommitautopep8.py
autocommitautopep8-0.3.1.dist-info/METADATA
autocommitautopep8-0.3.1.dist-info/WHEEL
autocommitautopep8-0.3.1.dist-info/entry_points.txt
autocommitautopep8-0.3.1.dist-info/top_level.txt
autocommitautopep8-0.3.1.dist-info/RECORD
