Metadata-Version: 2.1
Name: autocommitautopep8
Version: 0.3.1
Summary: auto generate git/hg commits per autopep8 fixes
Home-page: https://github.com/Psycojoker/autocommitautopep8
Author: Laurent Peuch
Author-email: cortex@worlddomination.be
License: gplv3+
Keywords: pep8 autopep8 formatting
Platform: UNKNOWN
Requires-Dist: autopep8
